squadai/__init__.py
squadai/agent.py
squadai/crew.py
squadai/llm.py
squadai/process.py
squadai/task.py
squadai/agents/__init__.py
squadai/agents/crew_agent_executor.py
squadai/agents/parser.py
squadai/agents/tools_handler.py
squadai/agents/agent_builder/__init__.py
squadai/agents/agent_builder/base_agent.py
squadai/agents/agent_builder/base_agent_executor_mixin.py
squadai/agents/agent_builder/utilities/__init__.py
squadai/agents/agent_builder/utilities/base_output_converter.py
squadai/agents/agent_builder/utilities/base_token_process.py
squadai/agents/cache/__init__.py
squadai/agents/cache/cache_handler.py
squadai/cli/__init__.py
squadai/cli/add_crew_to_flow.py
squadai/cli/cli.py
squadai/cli/command.py
squadai/cli/config.py
squadai/cli/constants.py
squadai/cli/create_crew.py
squadai/cli/create_flow.py
squadai/cli/evaluate_crew.py
squadai/cli/git.py
squadai/cli/install_crew.py
squadai/cli/kickoff_flow.py
squadai/cli/plot_flow.py
squadai/cli/plus_api.py
squadai/cli/provider.py
squadai/cli/replay_from_task.py
squadai/cli/reset_memories_command.py
squadai/cli/run_crew.py
squadai/cli/train_crew.py
squadai/cli/update_crew.py
squadai/cli/utils.py
squadai/cli/version.py
squadai/cli/authentication/__init__.py
squadai/cli/authentication/constants.py
squadai/cli/authentication/main.py
squadai/cli/authentication/token.py
squadai/cli/authentication/utils.py
squadai/cli/deploy/__init__.py
squadai/cli/deploy/main.py
squadai/cli/templates/__init__.py
squadai/cli/templates/crew/.gitignore
squadai/cli/templates/crew/README.md
squadai/cli/templates/crew/__init__.py
squadai/cli/templates/crew/crew.py
squadai/cli/templates/crew/main.py
squadai/cli/templates/crew/pyproject.toml
squadai/cli/templates/crew/config/agents.yaml
squadai/cli/templates/crew/config/tasks.yaml
squadai/cli/templates/crew/knowledge/user_preference.txt
squadai/cli/templates/crew/tools/__init__.py
squadai/cli/templates/crew/tools/custom_tool.py
squadai/cli/templates/flow/.gitignore
squadai-0.87.0.dist-info/METADATA
squadai-0.87.0.dist-info/WHEEL
squadai-0.87.0.dist-info/entry_points.txt
squadai-0.87.0.dist-info/licenses/LICENSE
squadai-0.87.0.dist-info/RECORD
